dssamble/__init__.py
dssamble/cli.py
dssamble/utils.py
dssamble/commands/__init__.py
dssamble/commands/create.py
dssamble/commands/createfiles.py
dssamble/commands/info.py
dssamble/security/__init__.py
dssamble/security/basic.py
dssamble/security/createfiles.py
dssamble/security/fullstack.py
dssamble-0.1.2.dist-info/METADATA
dssamble-0.1.2.dist-info/WHEEL
dssamble-0.1.2.dist-info/entry_points.txt
dssamble-0.1.2.dist-info/top_level.txt
dssamble-0.1.2.dist-info/RECORD
