Metadata-Version: 2.4
Name: dssamble
Version: 0.1.2
Summary: ⚡ CLI инструмент для генерации структуры проектов
Author-email: Dan <dandasakami@gmail.com>
Project-URL: Homepage, https://github.com/Dasakami/dssamble
Project-URL: Repository, https://github.com/Dasakami/dssamble
Project-URL: Bug Tracker, https://github.com/Dasakami/dssamble/issues
Keywords: cli,project-generator,fastapi,scaffold
Requires-Python: >=3.10
Requires-Dist: click>=8.1.0
